{"aboba":{"id":4,"creationDate":"2025-03-05T00:23:53","name":"1","price":1,"discount":1.0,"refundable":true,"coordinates":{"x":1.0,"y":1.0},"type":"VIP","event":{"id":2,"name":"1","ticketsCount":11,"description":"1"}},"aboba3":{"id":6,"creationDate":"2025-03-05T00:24:16","name":"3","price":3,"discount":3.0,"refundable":true,"coordinates":{"x":3.0,"y":3.0},"type":"CHEAP","event":{"id":3,"name":"3","ticketsCount":3,"description":"3"}},"aboba2":{"id":5,"creationDate":"2025-03-05T00:24:02","name":"2","price":2,"discount":2.0,"refundable":false,"coordinates":{"x":2.0,"y":2.0},"type":"BUDGETARY"},"negaaboba":{"id":7,"creationDate":"2025-03-08T22:32:09","name":"Amogus","price":1500,"discount":5.0,"refundable":true,"coordinates":{"x":15.0,"y":36.0},"type":"BUDGETARY","event":{"id":4,"name":"Och Kruto","ticketsCount":125,"description":"Ну, я"}}}